aidial_rag_eval/__init__.py
aidial_rag_eval/dataframe/__init__.py
aidial_rag_eval/dataframe/match_facts.py
aidial_rag_eval/dataframe/merge.py
aidial_rag_eval/dataframe/metrics.py
aidial_rag_eval/dataset.py
aidial_rag_eval/evaluate.py
aidial_rag_eval/facts/__init__.py
aidial_rag_eval/facts/citation.py
aidial_rag_eval/facts/exact.py
aidial_rag_eval/facts/match_str_facts.py
aidial_rag_eval/generation/__init__.py
aidial_rag_eval/generation/inference.py
aidial_rag_eval/generation/metric_binds.py
aidial_rag_eval/generation/models/__init__.py
aidial_rag_eval/generation/models/converters/__init__.py
aidial_rag_eval/generation/models/converters/base_converter.py
aidial_rag_eval/generation/models/converters/decontextualization_template.py
aidial_rag_eval/generation/models/converters/llm_decontextualization_converter.py
aidial_rag_eval/generation/models/inference_scorers/__init__.py
aidial_rag_eval/generation/models/inference_scorers/base_inference_scorer.py
aidial_rag_eval/generation/models/inference_scorers/inference_template.py
aidial_rag_eval/generation/models/inference_scorers/llm_inference_scorer.py
aidial_rag_eval/generation/models/lambdas.py
aidial_rag_eval/generation/models/refusal_detectors/__init__.py
aidial_rag_eval/generation/models/refusal_detectors/base_refusal_detector.py
aidial_rag_eval/generation/models/refusal_detectors/llm_refusal_detector.py
aidial_rag_eval/generation/models/refusal_detectors/refusal_template.py
aidial_rag_eval/generation/models/statement_extractor/__init__.py
aidial_rag_eval/generation/models/statement_extractor/base_statement_extractor.py
aidial_rag_eval/generation/models/statement_extractor/llm_statement_extractor.py
aidial_rag_eval/generation/models/statement_extractor/statement_extractor_template.py
aidial_rag_eval/generation/refusal.py
aidial_rag_eval/generation/types.py
aidial_rag_eval/generation/utils/__init__.py
aidial_rag_eval/generation/utils/progress_bar.py
aidial_rag_eval/generation/utils/segmented_text.py
aidial_rag_eval-0.4.0.dist-info/LICENSE
aidial_rag_eval-0.4.0.dist-info/METADATA
aidial_rag_eval-0.4.0.dist-info/WHEEL
aidial_rag_eval-0.4.0.dist-info/RECORD
