Metadata-Version: 2.1
Name: aidial-rag-eval
Version: 0.4.0
Summary: Library for RAG evaluation
Home-page: https://github.com/epam/ai-dial-rag-eval
License: Apache-2.0
Keywords: ai
Author: EPAM RAIL
Author-email: SpecialEPM-DIALDevTeam@epam.com
Requires-Python: >=3.11,<4.0
Classifier: License :: OSI Approved :: Apache Software License
Classifier: Programming Language :: Python :: 3
Classifier: Programming Language :: Python :: 3.11
Classifier: Programming Language :: Python :: 3.12
Classifier: Programming Language :: Python :: 3.13
Classifier: Topic :: Software Development :: Libraries :: Python Modules
Provides-Extra: s3fs
Requires-Dist: fsspec (>=2024.3.1,<2025.0.0)
Requires-Dist: langchain-core (>=0.3.72,<2)
Requires-Dist: more-itertools (>=10.5.0,<11.0.0)
Requires-Dist: nltk (>=3.8.1,<4.0.0)
Requires-Dist: numpy (>=1.26.4,<3)
Requires-Dist: pandas (>=2.2.2,<3.0.0)
Requires-Dist: pyarrow (>=20.0.0,<21.0.0)
Requires-Dist: pydantic (>=2.7.1,<3.0.0)
Requires-Dist: s3fs (>=2024.3.1,<2025.0.0) ; extra == "s3fs"
Requires-Dist: tqdm (>=4.66.4,<5.0.0)
Project-URL: Documentation, https://github.com/epam/ai-dial-rag-eval
Project-URL: Repository, https://github.com/epam/ai-dial-rag-eval
